keep_presence/__init__.py
keep_presence/__main__.py
keep_presence-1.0.7.1.dist-info/LICENSE
keep_presence-1.0.7.1.dist-info/METADATA
keep_presence-1.0.7.1.dist-info/WHEEL
keep_presence-1.0.7.1.dist-info/entry_points.txt
keep_presence-1.0.7.1.dist-info/top_level.txt
keep_presence-1.0.7.1.dist-info/RECORD
