Metadata-Version: 2.1
Name: keep-presence
Version: 1.0.7.1
Summary: Keeps your computer awake by moving the mouse or pressing a key when you step away.
Author: carrot69
Project-URL: Homepage, https://github.com/carrot69/keep-presence
Project-URL: Bug Tracker, https://github.com/carrot69/keep-presence/issues
Requires-Python: >=3.7
License-File: LICENSE
Requires-Dist: pynput
